MANIFEST.in
README.rst
pyproject.toml
setup.cfg
setup.py
foolbox/ext/native/VERSION
foolbox/ext/native/__init__.py
foolbox/ext/native/evaluate.py
foolbox/ext/native/norms.py
foolbox/ext/native/plot.py
foolbox/ext/native/tensorboard.py
foolbox/ext/native/utils.py
foolbox/ext/native/attacks/__init__.py
foolbox/ext/native/attacks/additive_noise.py
foolbox/ext/native/attacks/basic_iterative_method.py
foolbox/ext/native/attacks/binarization.py
foolbox/ext/native/attacks/blended_noise.py
foolbox/ext/native/attacks/blur.py
foolbox/ext/native/attacks/boundary_attack.py
foolbox/ext/native/attacks/brendel_bethge.py
foolbox/ext/native/attacks/carlini_wagner.py
foolbox/ext/native/attacks/contrast.py
foolbox/ext/native/attacks/dataset_attack.py
foolbox/ext/native/attacks/deepfool.py
foolbox/ext/native/attacks/ead.py
foolbox/ext/native/attacks/fast_gradient_method.py
foolbox/ext/native/attacks/inversion.py
foolbox/ext/native/attacks/projected_gradient_descent.py
foolbox/ext/native/attacks/saltandpepper.py
foolbox/ext/native/models/__init__.py
foolbox/ext/native/models/base.py
foolbox/ext/native/models/foolbox.py
foolbox/ext/native/models/jax.py
foolbox/ext/native/models/pytorch.py
foolbox/ext/native/models/tensorflow.py
foolbox_native.egg-info/PKG-INFO
foolbox_native.egg-info/SOURCES.txt
foolbox_native.egg-info/dependency_links.txt
foolbox_native.egg-info/not-zip-safe
foolbox_native.egg-info/requires.txt
foolbox_native.egg-info/top_level.txt