Metadata-Version: 2.1
Name: foolbox-native
Version: 0.8.0
Summary: Foolbox Native is an extension for Foolbox that tries to bring native performance to Foolbox. This extension is a prototype with the goal of ultimately becoming part of Foolbox itself.
Home-page: https://github.com/jonasrauber/foolbox-native
Author: Jonas Rauber
Author-email: git@jonasrauber.de
License: UNKNOWN
Platform: UNKNOWN
Classifier: Development Status :: 3 - Alpha
Classifier: Intended Audience :: Developers
Classifier: Intended Audience :: Science/Research
Classifier: License :: OSI Approved :: MIT License
Classifier: Programming Language :: Python :: 3
Classifier: Programming Language :: Python :: 3.6
Classifier: Topic :: Scientific/Engineering :: Artificial Intelligence
Provides-Extra: testing
